LICENSE
MANIFEST.in
README.md
config.ini
setup.py
tox.ini
fedscm_admin/__init__.py
fedscm_admin/bugzilla.py
fedscm_admin/config.py
fedscm_admin/exceptions.py
fedscm_admin/fas.py
fedscm_admin/fedscm_admin.py
fedscm_admin/git.py
fedscm_admin/pagure.py
fedscm_admin/pdc.py
fedscm_admin/request_utils.py
fedscm_admin/utils.py
fedscm_admin.egg-info/PKG-INFO
fedscm_admin.egg-info/SOURCES.txt
fedscm_admin.egg-info/dependency_links.txt
fedscm_admin.egg-info/entry_points.txt
fedscm_admin.egg-info/requires.txt
fedscm_admin.egg-info/top_level.txt
tests/__init__.py
tests/mock_values.py
tests/test_admin.py
tests/test_config.ini
tests/test_general.py